rowan/__init__.py
rowan/constants.py
rowan/folder.py
rowan/project.py
rowan/protein.py
rowan/py.typed
rowan/user.py
rowan/utils.py
rowan/workflow.py
rowan/rowan_rdkit/__init__.py
rowan/rowan_rdkit/chem_utils.py
rowan_python-2.1.13.dist-info/METADATA
rowan_python-2.1.13.dist-info/WHEEL
rowan_python-2.1.13.dist-info/licenses/LICENSE
rowan_python-2.1.13.dist-info/RECORD
