Metadata-Version: 2.4
Name: rowan-python
Version: 2.1.13
Summary: Rowan Python Library
Project-URL: Homepage, https://github.com/rowansci/rowan-client
Project-URL: Bug Tracker, https://github.com/rowansci/rowan-client/issues
Author-email: Corin Wagen <corin@rowansci.com>
License-File: LICENSE
Requires-Python: >=3.11
Requires-Dist: httpx
Requires-Dist: nest-asyncio
Requires-Dist: rdkit
Requires-Dist: setuptools
Requires-Dist: stjames>=0.0.144
